selene/__init__.py
selene/browser.py
selene/browsers.py
selene/bys.py
selene/conditions.py
selene/config.py
selene/driver.py
selene/elements.py
selene/environment.py
selene/exceptions.py
selene/factory.py
selene/helpers.py
selene/version.py
selene/wait.py
selene/abctypes/__init__.py
selene/abctypes/conditions.py
selene/abctypes/locators.py
selene/abctypes/search_context.py
selene/abctypes/webdriver.py
selene/abctypes/webelement.py
selene/api/__init__.py
selene/common/__init__.py
selene/common/delegation.py
selene/common/fp.py
selene/common/none_object.py
selene/common/predicate.py
selene/support/__init__.py
selene/support/by.py
selene/support/jquery_style_selectors.py
selene/support/conditions/__init__.py
selene/support/conditions/be.py
selene/support/conditions/have.py
selene-1.0.1.dist-info/LICENSE
selene-1.0.1.dist-info/METADATA
selene-1.0.1.dist-info/WHEEL
selene-1.0.1.dist-info/top_level.txt
selene-1.0.1.dist-info/RECORD
